metamorph_mda_parser/__init__.py
metamorph_mda_parser/lark.py
metamorph_mda_parser/nd.py
metamorph_mda_parser/nd_grammar.lark
metamorph_mda_parser/xarray.py
metamorph_mda_parser-0.1.5.dist-info/METADATA
metamorph_mda_parser-0.1.5.dist-info/WHEEL
metamorph_mda_parser-0.1.5.dist-info/licenses/LICENSE.txt
metamorph_mda_parser-0.1.5.dist-info/RECORD
