Metadata-Version: 2.3
Name: metamorph-mda-parser
Version: 0.1.5
Summary: Light-weight parsing of Metamorph/VisiView .nd files.
Project-URL: Documentation, https://github.com/fmi-faim/metamorph-mda-parser#readme
Project-URL: Issues, https://github.com/fmi-faim/metamorph-mda-parser/issues
Project-URL: Source, https://github.com/fmi-faim/metamorph-mda-parser
Author-email: Jan Eglinger <jan.eglinger@fmi.ch>
License: BSD-3-Clause
Classifier: Development Status :: 4 - Beta
Classifier: Programming Language :: Python
Classifier: Programming Language :: Python :: 3.10
Classifier: Programming Language :: Python :: 3.11
Classifier: Programming Language :: Python :: 3.12
Classifier: Programming Language :: Python :: Implementation :: CPython
Classifier: Programming Language :: Python :: Implementation :: PyPy
Requires-Python: >=3.10
Requires-Dist: lark
Requires-Dist: pandas
Requires-Dist: pydantic
Provides-Extra: xarray
Requires-Dist: dask; extra == 'xarray'
Requires-Dist: numpy<2; extra == 'xarray'
Requires-Dist: tifffile; extra == 'xarray'
Requires-Dist: xarray; extra == 'xarray'
Requires-Dist: zarr; extra == 'xarray'
